<?xml version="1.0"?>
<!DOCTYPE hibernate-mapping PUBLIC "-//Hibernate/Hibernate Mapping DTD 3.0//EN"
"http://hibernate.sourceforge.net/hibernate-mapping-3.0.dtd">
<!-- Generated Jan 25, 2013 10:16:34 AM by Hibernate Tools 3.4.0.CR1 -->
<hibernate-mapping package="lu.itrust.business.TS">
	<class name="Measure" table="measure" abstract="true">
		<id name="id" column="idMeasure" unsaved-value="-1">
			<generator class="increment" />
		</id>
		<many-to-one name="analysisNorm" column="fiAnalysisNorm" cascade="save-update" not-null="true" />
		<many-to-one cascade="save-update" name="measureDescription" column="fiMeasureDescription" not-null="true" lazy="false" access="field" />
		<many-to-one name="phase" column="fiPhase" cascade="save-update" not-null="true" access="field" />
		<property name="computable" column="dtComputable" not-null="true" />
		<property name="status" column="dtStatus" not-null="true" />
		<property name="internalWL" column="dtInternalWorkLoad" not-null="true" access="field" />
		<property name="externalWL" column="dtExternalWorkLoad" not-null="true" access="field" />
		<property name="investment" column="dtInvestment" not-null="true" access="field" />
		<property name="lifetime" column="dtLifetime" not-null="true" access="field" />
		<property name="maintenance" column="dtMaintenance" not-null="true" access="field" />
		<property name="cost" column="dtCost" not-null="true" access="field" />
		<property name="comment" column="dtComment" type="text" />
		<property name="toDo" column="dtToDo" type="text" />
		<joined-subclass name="MaturityMeasure" extends="Measure" table="maturityMeasure">
			<key column="idMaturityMeasure" not-null="true" />
			<many-to-one name="implementationRate" column="fiImplementationRateParameter" not-null="true" access="field" />
			<property name="reachedLevel" column="dtReachedLevel" not-null="true" />
			<property name="SML1Cost" column="dtSML1Cost" not-null="true" />
			<property name="SML2Cost" column="dtSML2Cost" not-null="true" />
			<property name="SML3Cost" column="dtSML3Cost" not-null="true" />
			<property name="SML4Cost" column="dtSML4Cost" not-null="true" />
			<property name="SML5Cost" column="dtSML5Cost" not-null="true" />
		</joined-subclass>
		<joined-subclass name="NormMeasure" extends="Measure" table="normMeasure">
			<key column="idNormMeasure" not-null="true" />
			<many-to-one name="measurePropertyList" column="fiMeasureProperties" cascade="all" not-null="true" />
			<property name="implementationRate" access="field" column="dtImplementationRate" not-null="true" />
			<property name="toCheck" column="dtToCheck" />
			<bag name="assetTypeValues" table="measureAssetTypeValue" cascade="all">
				<key column="idNormMeasure" not-null="true" />
				<many-to-many class="AssetTypeValue" column="idMeasureAssetTypeValue" unique="true" />
			</bag>
		</joined-subclass>
	</class>
</hibernate-mapping>